{"ref": "xyz.parlatype.Parlatype", "stats": [{"date": "2024/06/05", "arches": {"aarch64": [2, 0], "x86_64": [275, 18]}}, {"date": "2024/06/06", "arches": {"x86_64": [224, 54]}}, {"date": "2024/06/07", "arches": {"x86_64": [75, 4]}}, {"date": "2024/06/08", "arches": {"x86_64": [45, 1]}}, {"date": "2024/06/09", "arches": {"aarch64": [2, 0], "x86_64": [65, 1]}}, {"date": "2024/06/10", "arches": {"x86_64": [32, 5]}}, {"date": "2024/06/11", "arches": {"x86_64": [21, 3]}}, {"date": "2024/06/12", "arches": {"x86_64": [31, 1]}}, {"date": "2024/06/13", "arches": {"aarch64": [2, 0], "x86_64": [20, 3]}}, {"date": "2024/06/14", "arches": {"x86_64": [36, 0]}}, {"date": "2024/06/15", "arches": {"x86_64": [13, 0]}}]}